Metadata-Version: 2.4
Name: ia-manager
Version: 1.0.1
Summary: A Python package to scrape and download files from the Internet Archive.
Home-page: https://github.com/vichmartins/internet-archive-downloader
Author: vichmartins
Classifier: Programming Language :: Python :: 3
Classifier: License :: OSI Approved :: MIT License
Classifier: Operating System :: OS Independent
Requires-Python: >=3.10
Requires-Dist: requests>=2.26.0
Requires-Dist: beautifulsoup4>=4.10.0
Requires-Dist: tqdm>=4.62.0
Dynamic: author
Dynamic: classifier
Dynamic: description
Dynamic: description-content-type
Dynamic: home-page
Dynamic: requires-dist
Dynamic: requires-python
Dynamic: summary
